Workbook

Sheet Dashboard
A1: ARR Banana Store dashboard
A2: Change the month in the yellow cell. Everything else is calculated from the input tabs.
A3: Month | B3: 46296
A5: Sales | B5: Main | C5: Rizal | D5: Total
A6: Retail sales | B6: =SUMIFS('Daily Sales'!$C:$C,'Daily Sales'!$B:$B,B$5,'Daily Sales'!$A:$A,">="&$B$3,'Daily Sales'!$A:$A,"<"&EDATE($B$3,1)) | C6: =SUMIFS('Daily Sales'!$C:$C,'Daily Sales'!$B:$B,C$5,'Daily Sales'!$A:$A,">="&$B$3,'Daily Sales'!$A:$A,"<"&EDATE($B$3,1)) | D6: =SUM(B6:C6)
A7: Wholesale sales | B7: =SUMIFS('Daily Sales'!$D:$D,'Daily Sales'!$B:$B,B$5,'Daily Sales'!$A:$A,">="&$B$3,'Daily Sales'!$A:$A,"<"&EDATE($B$3,1)) | C7: =SUMIFS('Daily Sales'!$D:$D,'Daily Sales'!$B:$B,C$5,'Daily Sales'!$A:$A,">="&$B$3,'Daily Sales'!$A:$A,"<"&EDATE($B$3,1)) | D7: =SUM(B7:C7)
A8: Total sales | B8: =B6+B7 | C8: =C6+C7 | D8: =SUM(B8:C8)
A9: Spoilage at cost | B9: =SUMIFS('Daily Sales'!$F:$F,'Daily Sales'!$B:$B,B$5,'Daily Sales'!$A:$A,">="&$B$3,'Daily Sales'!$A:$A,"<"&EDATE($B$3,1)) | C9: =SUMIFS('Daily Sales'!$F:$F,'Daily Sales'!$B:$B,C$5,'Daily Sales'!$A:$A,">="&$B$3,'Daily Sales'!$A:$A,"<"&EDATE($B$3,1)) | D9: =SUM(B9:C9)
A10: Spoilage, % of sales | B10: =IF(B8=0,0,B9/B8) | C10: =IF(C8=0,0,C9/C8) | D10: =IF(D8=0,0,D9/D8)
A11: Cash short (-) / over (+) | B11: =SUMIFS('Daily Sales'!$E:$E,'Daily Sales'!$B:$B,B$5,'Daily Sales'!$A:$A,">="&$B$3,'Daily Sales'!$A:$A,"<"&EDATE($B$3,1)) | C11: =SUMIFS('Daily Sales'!$E:$E,'Daily Sales'!$B:$B,C$5,'Daily Sales'!$A:$A,">="&$B$3,'Daily Sales'!$A:$A,"<"&EDATE($B$3,1)) | D11: =SUM(B11:C11)
A12: Days reported | B12: =COUNTIFS('Daily Sales'!$B:$B,B$5,'Daily Sales'!$A:$A,">="&$B$3,'Daily Sales'!$A:$A,"<"&EDATE($B$3,1)) | C12: =COUNTIFS('Daily Sales'!$B:$B,C$5,'Daily Sales'!$A:$A,">="&$B$3,'Daily Sales'!$A:$A,"<"&EDATE($B$3,1))
A14: Cost of fruit (whole business) | D14: Total
A15: Fruit purchases | D15: =SUMIFS(Deliveries!$E:$E,'Deliveries'!$A:$A,">="&$B$3,'Deliveries'!$A:$A,"<"&EDATE($B$3,1))
A16: Trucking & labor | D16: =SUMIFS(Expenses!$E:$E,Expenses!$C:$C,"Trucking & Labor",'Expenses'!$A:$A,">="&$B$3,'Expenses'!$A:$A,"<"&EDATE($B$3,1))
A17: Stock at start of month | D17: =SUMPRODUCT(('Stock Count'!$A$5:$A$5000=EDATE($B$3,-1))*'Stock Count'!$D$5:$D$5000*'Stock Count'!$E$5:$E$5000)
A18: Stock at end of month | D18: =SUMPRODUCT(('Stock Count'!$A$5:$A$5000=$B$3)*'Stock Count'!$D$5:$D$5000*'Stock Count'!$E$5:$E$5000)
A19: Cost of fruit sold | D19: =D15+D16+D17-D18
A20: Gross margin, % | D20: =IF(D8=0,0,(D8-D19)/D8)
A21: Kg delivered (rows with kg filled in) | D21: =SUMIFS(Deliveries!$D:$D,'Deliveries'!$A:$A,">="&$B$3,'Deliveries'!$A:$A,"<"&EDATE($B$3,1))
A22: Profit | B22: Main | C22: Rizal | D22: Total
A23: Gross profit (branch split by share of sales) | B23: =B8*$D$20 | C23: =C8*$D$20 | D23: =D8-D19
A24: Operating expenses | B24: =SUMIFS(Expenses!$E:$E,Expenses!$B:$B,B$22,'Expenses'!$A:$A,">="&$B$3,'Expenses'!$A:$A,"<"&EDATE($B$3,1))-SUMIFS(Expenses!$E:$E,Expenses!$B:$B,B$22,Expenses!$C:$C,"Trucking & Labor",'Expenses'!$A:$A,">="&$B$3,'Expenses'!$A:$A,"<"&EDATE($B$3,1)) | C24: =SUMIFS(Expenses!$E:$E,Expenses!$B:$B,C$22,'Expenses'!$A:$A,">="&$B$3,'Expenses'!$A:$A,"<"&EDATE($B$3,1))-SUMIFS(Expenses!$E:$E,Expenses!$B:$B,C$22,Expenses!$C:$C,"Trucking & Labor",'Expenses'!$A:$A,">="&$B$3,'Expenses'!$A:$A,"<"&EDATE($B$3,1)) | D24: =SUM(B24:C24)
A25: of which staff (salary + cash advances) | B25: =SUMIFS(Expenses!$E:$E,Expenses!$B:$B,B$22,Expenses!$C:$C,"Salary (net paid)",'Expenses'!$A:$A,">="&$B$3,'Expenses'!$A:$A,"<"&EDATE($B$3,1))+SUMIFS(Expenses!$E:$E,Expenses!$B:$B,B$22,Expenses!$C:$C,"Cash Advance",'Expenses'!$A:$A,">="&$B$3,'Expenses'!$A:$A,"<"&EDATE($B$3,1)) | C25: =SUMIFS(Expenses!$E:$E,Expenses!$B:$B,C$22,Expenses!$C:$C,"Salary (net paid)",'Expenses'!$A:$A,">="&$B$3,'Expenses'!$A:$A,"<"&EDATE($B$3,1))+SUMIFS(Expenses!$E:$E,Expenses!$B:$B,C$22,Expenses!$C:$C,"Cash Advance",'Expenses'!$A:$A,">="&$B$3,'Expenses'!$A:$A,"<"&EDATE($B$3,1)) | D25: =SUM(B25:C25)
A26: Net profit | B26: =B23-B24 | C26: =C23-C24 | D26: =D23-D24
A27: Net margin, % | B27: =IF(B8=0,0,B26/B8) | C27: =IF(C8=0,0,C26/C8) | D27: =IF(D8=0,0,D26/D8)
A29: Alerts | B29: Main | C29: Rizal
A30: Days missing a report (so far this month) | B30: =MAX(0,$B$35-B12) | C30: =MAX(0,$B$35-C12)
A31: Days cash was short by more than the limit | B31: =COUNTIFS('Daily Sales'!$B:$B,B$29,'Daily Sales'!$A:$A,">="&$B$3,'Daily Sales'!$A:$A,"<"&EDATE($B$3,1),'Daily Sales'!$E:$E,"<"&-Settings!$F$5) | C31: =COUNTIFS('Daily Sales'!$B:$B,C$29,'Daily Sales'!$A:$A,">="&$B$3,'Daily Sales'!$A:$A,"<"&EDATE($B$3,1),'Daily Sales'!$E:$E,"<"&-Settings!$F$5)
A32: Spoilage above the limit | B32: =IF(B10>Settings!$F$6,"CHECK","OK") | C32: =IF(C10>Settings!$F$6,"CHECK","OK")
A33: Stock count for this month entered | B33: =IF(COUNTIFS('Stock Count'!$A:$A,$B$3)>0,"Yes","No: until counted, profit treats all fruit bought this month as sold")
A35: Days so far this month | B35: =MAX(0,MIN(TODAY(),EOMONTH($B$3,0))-$B$3+1)
A37: How profit is worked out: cost of fruit sold = purchases + trucking + stock at start - stock at end. Branch gross profit is estimated by each branch's share of sales, because deliveries are shared.

Sheet Monthly Trend
A1: Monthly trend, 2026
A2: Calculated from the input tabs. Months before October 2026 are on the History tab.
A4: Month | B4: 46023 | C4: 46054 | D4: 46082 | E4: 46113 | F4: 46143 | G4: 46174 | H4: 46204 | I4: 46235 | J4: 46266 | K4: 46296 | L4: 46327 | M4: 46357
A5: Total sales | B5: =SUMIFS('Daily Sales'!$C:$C,'Daily Sales'!$A:$A,">="&B$4,'Daily Sales'!$A:$A,"<"&EDATE(B$4,1))+SUMIFS('Daily Sales'!$D:$D,'Daily Sales'!$A:$A,">="&B$4,'Daily Sales'!$A:$A,"<"&EDATE(B$4,1)) | C5: =SUMIFS('Daily Sales'!$C:$C,'Daily Sales'!$A:$A,">="&C$4,'Daily Sales'!$A:$A,"<"&EDATE(C$4,1))+SUMIFS('Daily Sales'!$D:$D,'Daily Sales'!$A:$A,">="&C$4,'Daily Sales'!$A:$A,"<"&EDATE(C$4,1)) | D5: =SUMIFS('Daily Sales'!$C:$C,'Daily Sales'!$A:$A,">="&D$4,'Daily Sales'!$A:$A,"<"&EDATE(D$4,1))+SUMIFS('Daily Sales'!$D:$D,'Daily Sales'!$A:$A,">="&D$4,'Daily Sales'!$A:$A,"<"&EDATE(D$4,1)) | E5: =SUMIFS('Daily Sales'!$C:$C,'Daily Sales'!$A:$A,">="&E$4,'Daily Sales'!$A:$A,"<"&EDATE(E$4,1))+SUMIFS('Daily Sales'!$D:$D,'Daily Sales'!$A:$A,">="&E$4,'Daily Sales'!$A:$A,"<"&EDATE(E$4,1)) | F5: =SUMIFS('Daily Sales'!$C:$C,'Daily Sales'!$A:$A,">="&F$4,'Daily Sales'!$A:$A,"<"&EDATE(F$4,1))+SUMIFS('Daily Sales'!$D:$D,'Daily Sales'!$A:$A,">="&F$4,'Daily Sales'!$A:$A,"<"&EDATE(F$4,1)) | G5: =SUMIFS('Daily Sales'!$C:$C,'Daily Sales'!$A:$A,">="&G$4,'Daily Sales'!$A:$A,"<"&EDATE(G$4,1))+SUMIFS('Daily Sales'!$D:$D,'Daily Sales'!$A:$A,">="&G$4,'Daily Sales'!$A:$A,"<"&EDATE(G$4,1)) | H5: =SUMIFS('Daily Sales'!$C:$C,'Daily Sales'!$A:$A,">="&H$4,'Daily Sales'!$A:$A,"<"&EDATE(H$4,1))+SUMIFS('Daily Sales'!$D:$D,'Daily Sales'!$A:$A,">="&H$4,'Daily Sales'!$A:$A,"<"&EDATE(H$4,1)) | I5: =SUMIFS('Daily Sales'!$C:$C,'Daily Sales'!$A:$A,">="&I$4,'Daily Sales'!$A:$A,"<"&EDATE(I$4,1))+SUMIFS('Daily Sales'!$D:$D,'Daily Sales'!$A:$A,">="&I$4,'Daily Sales'!$A:$A,"<"&EDATE(I$4,1)) | ... M5: =SUMIFS('Daily Sales'!$C:$C,'Daily Sales'!$A:$A,">="&M$4,'Daily Sales'!$A:$A,"<"&EDATE(M$4,1))+SUMIFS('Daily Sales'!$D:$D,'Daily Sales'!$A:$A,">="&M$4,'Daily Sales'!$A:$A,"<"&EDATE(M$4,1))
A6: Cost of fruit sold | B6: =SUMIFS(Deliveries!$E:$E,'Deliveries'!$A:$A,">="&B$4,'Deliveries'!$A:$A,"<"&EDATE(B$4,1))+SUMIFS(Expenses!$E:$E,Expenses!$C:$C,"Trucking & Labor",'Expenses'!$A:$A,">="&B$4,'Expenses'!$A:$A,"<"&EDATE(B$4,1))+SUMPRODUCT(('Stock Count'!$A$5:$A$5000=EDATE(B$4,-1))*'Stock Count'!$D$5:$D$5000*'Stock Count'!$E$5:$E$5000)-SUMPRODUCT(('Stock Count'!$A$5:$A$5000=B$4)*'Stock Count'!$D$5:$D$5000*'Stock Count'!$E$5:$E$5000) | C6: =SUMIFS(Deliveries!$E:$E,'Deliveries'!$A:$A,">="&C$4,'Deliveries'!$A:$A,"<"&EDATE(C$4,1))+SUMIFS(Expenses!$E:$E,Expenses!$C:$C,"Trucking & Labor",'Expenses'!$A:$A,">="&C$4,'Expenses'!$A:$A,"<"&EDATE(C$4,1))+SUMPRODUCT(('Stock Count'!$A$5:$A$5000=EDATE(C$4,-1))*'Stock Count'!$D$5:$D$5000*'Stock Count'!$E$5:$E$5000)-SUMPRODUCT(('Stock Count'!$A$5:$A$5000=C$4)*'Stock Count'!$D$5:$D$5000*'Stock Count'!$E$5:$E$5000) | D6: =SUMIFS(Deliveries!$E:$E,'Deliveries'!$A:$A,">="&D$4,'Deliveries'!$A:$A,"<"&EDATE(D$4,1))+SUMIFS(Expenses!$E:$E,Expenses!$C:$C,"Trucking & Labor",'Expenses'!$A:$A,">="&D$4,'Expenses'!$A:$A,"<"&EDATE(D$4,1))+SUMPRODUCT(('Stock Count'!$A$5:$A$5000=EDATE(D$4,-1))*'Stock Count'!$D$5:$D$5000*'Stock Count'!$E$5:$E$5000)-SUMPRODUCT(('Stock Count'!$A$5:$A$5000=D$4)*'Stock Count'!$D$5:$D$5000*'Stock Count'!$E$5:$E$5000) | E6: =SUMIFS(Deliveries!$E:$E,'Deliveries'!$A:$A,">="&E$4,'Deliveries'!$A:$A,"<"&EDATE(E$4,1))+SUMIFS(Expenses!$E:$E,Expenses!$C:$C,"Trucking & Labor",'Expenses'!$A:$A,">="&E$4,'Expenses'!$A:$A,"<"&EDATE(E$4,1))+SUMPRODUCT(('Stock Count'!$A$5:$A$5000=EDATE(E$4,-1))*'Stock Count'!$D$5:$D$5000*'Stock Count'!$E$5:$E$5000)-SUMPRODUCT(('Stock Count'!$A$5:$A$5000=E$4)*'Stock Count'!$D$5:$D$5000*'Stock Count'!$E$5:$E$5000) | F6: =SUMIFS(Deliveries!$E:$E,'Deliveries'!$A:$A,">="&F$4,'Deliveries'!$A:$A,"<"&EDATE(F$4,1))+SUMIFS(Expenses!$E:$E,Expenses!$C:$C,"Trucking & Labor",'Expenses'!$A:$A,">="&F$4,'Expenses'!$A:$A,"<"&EDATE(F$4,1))+SUMPRODUCT(('Stock Count'!$A$5:$A$5000=EDATE(F$4,-1))*'Stock Count'!$D$5:$D$5000*'Stock Count'!$E$5:$E$5000)-SUMPRODUCT(('Stock Count'!$A$5:$A$5000=F$4)*'Stock Count'!$D$5:$D$5000*'Stock Count'!$E$5:$E$5000) | G6: =SUMIFS(Deliveries!$E:$E,'Deliveries'!$A:$A,">="&G$4,'Deliveries'!$A:$A,"<"&EDATE(G$4,1))+SUMIFS(Expenses!$E:$E,Expenses!$C:$C,"Trucking & Labor",'Expenses'!$A:$A,">="&G$4,'Expenses'!$A:$A,"<"&EDATE(G$4,1))+SUMPRODUCT(('Stock Count'!$A$5:$A$5000=EDATE(G$4,-1))*'Stock Count'!$D$5:$D$5000*'Stock Count'!$E$5:$E$5000)-SUMPRODUCT(('Stock Count'!$A$5:$A$5000=G$4)*'Stock Count'!$D$5:$D$5000*'Stock Count'!$E$5:$E$5000) | H6: =SUMIFS(Deliveries!$E:$E,'Deliveries'!$A:$A,">="&H$4,'Deliveries'!$A:$A,"<"&EDATE(H$4,1))+SUMIFS(Expenses!$E:$E,Expenses!$C:$C,"Trucking & Labor",'Expenses'!$A:$A,">="&H$4,'Expenses'!$A:$A,"<"&EDATE(H$4,1))+SUMPRODUCT(('Stock Count'!$A$5:$A$5000=EDATE(H$4,-1))*'Stock Count'!$D$5:$D$5000*'Stock Count'!$E$5:$E$5000)-SUMPRODUCT(('Stock Count'!$A$5:$A$5000=H$4)*'Stock Count'!$D$5:$D$5000*'Stock Count'!$E$5:$E$5000) | I6: =SUMIFS(Deliveries!$E:$E,'Deliveries'!$A:$A,">="&I$4,'Deliveries'!$A:$A,"<"&EDATE(I$4,1))+SUMIFS(Expenses!$E:$E,Expenses!$C:$C,"Trucking & Labor",'Expenses'!$A:$A,">="&I$4,'Expenses'!$A:$A,"<"&EDATE(I$4,1))+SUMPRODUCT(('Stock Count'!$A$5:$A$5000=EDATE(I$4,-1))*'Stock Count'!$D$5:$D$5000*'Stock Count'!$E$5:$E$5000)-SUMPRODUCT(('Stock Count'!$A$5:$A$5000=I$4)*'Stock Count'!$D$5:$D$5000*'Stock Count'!$E$5:$E$5000) | ... M6: =SUMIFS(Deliveries!$E:$E,'Deliveries'!$A:$A,">="&M$4,'Deliveries'!$A:$A,"<"&EDATE(M$4,1))+SUMIFS(Expenses!$E:$E,Expenses!$C:$C,"Trucking & Labor",'Expenses'!$A:$A,">="&M$4,'Expenses'!$A:$A,"<"&EDATE(M$4,1))+SUMPRODUCT(('Stock Count'!$A$5:$A$5000=EDATE(M$4,-1))*'Stock Count'!$D$5:$D$5000*'Stock Count'!$E$5:$E$5000)-SUMPRODUCT(('Stock Count'!$A$5:$A$5000=M$4)*'Stock Count'!$D$5:$D$5000*'Stock Count'!$E$5:$E$5000)
A7: Gross profit | B7: =B5-B6 | C7: =C5-C6 | D7: =D5-D6 | E7: =E5-E6 | F7: =F5-F6 | G7: =G5-G6 | H7: =H5-H6 | I7: =I5-I6 | ... M7: =M5-M6
A8: Operating expenses | B8: =SUMIFS(Expenses!$E:$E,'Expenses'!$A:$A,">="&B$4,'Expenses'!$A:$A,"<"&EDATE(B$4,1))-SUMIFS(Expenses!$E:$E,Expenses!$C:$C,"Trucking & Labor",'Expenses'!$A:$A,">="&B$4,'Expenses'!$A:$A,"<"&EDATE(B$4,1)) | C8: =SUMIFS(Expenses!$E:$E,'Expenses'!$A:$A,">="&C$4,'Expenses'!$A:$A,"<"&EDATE(C$4,1))-SUMIFS(Expenses!$E:$E,Expenses!$C:$C,"Trucking & Labor",'Expenses'!$A:$A,">="&C$4,'Expenses'!$A:$A,"<"&EDATE(C$4,1)) | D8: =SUMIFS(Expenses!$E:$E,'Expenses'!$A:$A,">="&D$4,'Expenses'!$A:$A,"<"&EDATE(D$4,1))-SUMIFS(Expenses!$E:$E,Expenses!$C:$C,"Trucking & Labor",'Expenses'!$A:$A,">="&D$4,'Expenses'!$A:$A,"<"&EDATE(D$4,1)) | E8: =SUMIFS(Expenses!$E:$E,'Expenses'!$A:$A,">="&E$4,'Expenses'!$A:$A,"<"&EDATE(E$4,1))-SUMIFS(Expenses!$E:$E,Expenses!$C:$C,"Trucking & Labor",'Expenses'!$A:$A,">="&E$4,'Expenses'!$A:$A,"<"&EDATE(E$4,1)) | F8: =SUMIFS(Expenses!$E:$E,'Expenses'!$A:$A,">="&F$4,'Expenses'!$A:$A,"<"&EDATE(F$4,1))-SUMIFS(Expenses!$E:$E,Expenses!$C:$C,"Trucking & Labor",'Expenses'!$A:$A,">="&F$4,'Expenses'!$A:$A,"<"&EDATE(F$4,1)) | G8: =SUMIFS(Expenses!$E:$E,'Expenses'!$A:$A,">="&G$4,'Expenses'!$A:$A,"<"&EDATE(G$4,1))-SUMIFS(Expenses!$E:$E,Expenses!$C:$C,"Trucking & Labor",'Expenses'!$A:$A,">="&G$4,'Expenses'!$A:$A,"<"&EDATE(G$4,1)) | H8: =SUMIFS(Expenses!$E:$E,'Expenses'!$A:$A,">="&H$4,'Expenses'!$A:$A,"<"&EDATE(H$4,1))-SUMIFS(Expenses!$E:$E,Expenses!$C:$C,"Trucking & Labor",'Expenses'!$A:$A,">="&H$4,'Expenses'!$A:$A,"<"&EDATE(H$4,1)) | I8: =SUMIFS(Expenses!$E:$E,'Expenses'!$A:$A,">="&I$4,'Expenses'!$A:$A,"<"&EDATE(I$4,1))-SUMIFS(Expenses!$E:$E,Expenses!$C:$C,"Trucking & Labor",'Expenses'!$A:$A,">="&I$4,'Expenses'!$A:$A,"<"&EDATE(I$4,1)) | ... M8: =SUMIFS(Expenses!$E:$E,'Expenses'!$A:$A,">="&M$4,'Expenses'!$A:$A,"<"&EDATE(M$4,1))-SUMIFS(Expenses!$E:$E,Expenses!$C:$C,"Trucking & Labor",'Expenses'!$A:$A,">="&M$4,'Expenses'!$A:$A,"<"&EDATE(M$4,1))
A9: Net profit | B9: =B7-B8 | C9: =C7-C8 | D9: =D7-D8 | E9: =E7-E8 | F9: =F7-F8 | G9: =G7-G8 | H9: =H7-H8 | I9: =I7-I8 | ... M9: =M7-M8
A10: Spoilage at cost | B10: =SUMIFS('Daily Sales'!$F:$F,'Daily Sales'!$A:$A,">="&B$4,'Daily Sales'!$A:$A,"<"&EDATE(B$4,1)) | C10: =SUMIFS('Daily Sales'!$F:$F,'Daily Sales'!$A:$A,">="&C$4,'Daily Sales'!$A:$A,"<"&EDATE(C$4,1)) | D10: =SUMIFS('Daily Sales'!$F:$F,'Daily Sales'!$A:$A,">="&D$4,'Daily Sales'!$A:$A,"<"&EDATE(D$4,1)) | E10: =SUMIFS('Daily Sales'!$F:$F,'Daily Sales'!$A:$A,">="&E$4,'Daily Sales'!$A:$A,"<"&EDATE(E$4,1)) | F10: =SUMIFS('Daily Sales'!$F:$F,'Daily Sales'!$A:$A,">="&F$4,'Daily Sales'!$A:$A,"<"&EDATE(F$4,1)) | G10: =SUMIFS('Daily Sales'!$F:$F,'Daily Sales'!$A:$A,">="&G$4,'Daily Sales'!$A:$A,"<"&EDATE(G$4,1)) | H10: =SUMIFS('Daily Sales'!$F:$F,'Daily Sales'!$A:$A,">="&H$4,'Daily Sales'!$A:$A,"<"&EDATE(H$4,1)) | I10: =SUMIFS('Daily Sales'!$F:$F,'Daily Sales'!$A:$A,">="&I$4,'Daily Sales'!$A:$A,"<"&EDATE(I$4,1)) | ... M10: =SUMIFS('Daily Sales'!$F:$F,'Daily Sales'!$A:$A,">="&M$4,'Daily Sales'!$A:$A,"<"&EDATE(M$4,1))

Sheet Settings
A1: Settings
A2: Blue cells are inputs. Change a threshold here and every alert uses it.
A4: Branches | C4: Expense categories | E4: Alert thresholds
A5: Main | C5: Rent | E5: Cash short alert, per day (₱) | F5: 300
A6: Rizal | C6: Salary (net paid) | E6: Spoilage alert, % of sales | F6: 0.05
C7: Cash Advance
C8: Food & Water
C9: Utilities
C10: Plastic
C11: Trash
C12: Repairs & Maintenance
C13: Ads & Tarpaulin
C14: Trucking & Labor
C15: Other

Sheet Daily Sales
A1: Daily sales
A2: One row per branch per day. Blue = typed in. Cash short is negative, surplus positive.
A4: Date | B4: Branch | C4: Retail sales (₱) | D4: Wholesale sales (₱) | E4: Cash short (-) / over (+) (₱) | F4: Spoilage at cost (₱) | G4: Lakatan sold (kg) | H4: Lakatan spoiled (kg) | I4: Notes
A5: 46296 | B5: Main | C5: 16180 | D5: 4543 | E5: 134.55
A6: 46296 | B6: Rizal | C6: 3118 | D6: 0 | E6: 397.75
A7: 46297 | B7: Main | C7: 14085 | D7: 0 | E7: 367.35
A8: 46297 | B8: Rizal | C8: 4765 | D8: 0 | E8: 75.05
A9: 46298 | B9: Main | C9: 17378 | D9: 868 | E9: 21.7
A10: 46298 | B10: Rizal | C10: 4246 | D10: 0 | E10: -310.85
A11: 46299 | B11: Main | C11: 21595 | D11: 9783 | E11: 446.7
A12: 46299 | B12: Rizal | C12: 4065 | D12: 0 | E12: -61.65
A13: 46300 | B13: Main | C13: 19770 | D13: 930 | E13: -667.5
A14: 46300 | B14: Rizal | C14: 5919 | D14: 0 | E14: 9.2
A15: 46301 | B15: Main | C15: 15876 | D15: 0 | E15: -369.55
A16: 46301 | B16: Rizal | C16: 3622 | D16: 0 | E16: 438.55

Sheet Deliveries
A1: Fruit deliveries
A2: One row per item per delivery. Trucking goes in Expenses as "Trucking & Labor".
A4: Date | B4: Supplier | C4: Item | D4: Kg | E4: Amount paid (₱) | F4: Notes
A5: 46301 | B5: Various | C5: All fruit | E5: 39250 | F5: 1-6 Oct total, itemized kg not available

Sheet Expenses
A1: Expenses
A2: Record cash advances when given (category "Cash Advance") and salary as the net amount paid.
A4: Date | B4: Branch | C4: Category | D4: Description | E4: Amount (₱) | F4: Paid from
A5: 46301 | B5: Main | C5: Plastic | D5: 1-6 Oct total from old expense sheet | E5: 57
A6: 46301 | B6: Main | C6: Trash | D6: 1-6 Oct total from old expense sheet | E6: 20
A7: 46301 | B7: Main | C7: Food & Water | D7: 1-6 Oct total from old expense sheet | E7: 2401
A8: 46301 | B8: Main | C8: Trucking & Labor | D8: 1-6 Oct total from old expense sheet | E8: 16612
A9: 46301 | B9: Rizal | C9: Food & Water | D9: 1-6 Oct total from old expense sheet | E9: 395
A10: 46301 | B10: Main | C10: Other | D10: 1-6 Oct total from old expense sheet | E10: 4025
A11: 46301 | B11: Rizal | C11: Ads & Tarpaulin | D11: 1-6 Oct total from old expense sheet | E11: 10

Sheet Stock Count
A1: Month-end stock count
A2: Count what is left on the last day of each month. "Month" = the month that just ended (first day).
A4: Month | B4: Branch | C4: Item | D4: Kg on hand | E4: Cost per kg (₱)

Sheet History
A1: History, Sep 2024 to Sep 2026
A2: Copied from the old Monthly Records dashboard. "Cash result" is sales minus cash spent that month, not profit.
A4: Month | B4: Sales (₱) | C4: Fruit purchases (₱) | D4: Expenses (₱) | E4: Cash result (₱)
A5: 45536 | B5: 103924.5 | C5: 108891 | D5: 5520 | E5: =B5-C5-D5
A6: 45566 | B6: 243188 | C6: 205831.68 | D6: 48945 | E6: =B6-C6-D6
A7: 45597 | B7: 366368 | C7: 277031 | D7: 67409 | E7: =B7-C7-D7
A8: 45627 | B8: 438406 | C8: 300098.41 | D8: 80345 | E8: =B8-C8-D8
A9: 45658 | B9: 338032 | C9: 235385 | D9: 83778 | E9: =B9-C9-D9
A10: 45689 | B10: 474913 | C10: 375314 | D10: 59348 | E10: =B10-C10-D10
A11: 45717 | B11: 517184 | C11: 329610 | D11: 97321 | E11: =B11-C11-D11
A12: 45748 | B12: 417827 | C12: 285512.3 | D12: 105578 | E12: =B12-C12-D12
A13: 45778 | B13: 416945 | C13: 309584 | D13: 98761 | E13: =B13-C13-D13
A14: 45809 | B14: 506844 | C14: 436211 | D14: 99756 | E14: =B14-C14-D14
A15: 45839 | B15: 535865 | C15: 311935 | D15: 100227.2 | E15: =B15-C15-D15
A16: 45870 | B16: 545055.5 | C16: 413359.5 | D16: 124109.17 | E16: =B16-C16-D16
... A29: 46266 | B29: 683641 | C29: 423224 | D29: 164778 | E29: =B29-C29-D29
A30: Total | B30: =SUM(B5:B29) | C30: =SUM(C5:C29) | D30: =SUM(D5:D29) | E30: =SUM(E5:E29)
